{"assets":[],"styles":[{"selectors":["c1032"],"style":{"top":"auto","bottom":"20px","right":"20px"}},{"selectors":["c1603"],"style":{"background":"url('../External/therapyTemplate/demos/therapy/images/about/about.jpg') no-repeat center center / cover"}},{"selectors":["c2375"],"style":{"transform":"translateY(70px)"}},{"selectors":["c3313"],"style":{"background":"url('../External/therapyTemplate/demos/therapy/images/price/cosmetic-1.jpg') no-repeat center center / cover"}},{"selectors":["c3423"],"style":{"background":"url('../External/therapyTemplate/demos/therapy/images/price/cosmetic-2.jpg') no-repeat right center / cover"}},{"selectors":["c4148"],"style":{"background":"url('../External/therapyTemplate/demos/therapy/images/rating.svg') no-repeat center center / 300px"}},{"selectors":["c4754"],"style":{"background":"url('https://source.unsplash.com/TU6ztds5LGg') no-repeat center center / cover"}},{"selectors":["c2357"],"style":{"background":"linear-gradient(rgba(0,0,0,.3), transparent), url('../External/therapyTemplate/demos/therapy/images/1.jpg') no-repeat center center / cover"}},{"selectors":["c4980"],"style":{"background":"url('../External/therapyTemplate/images/world-map.png') no-repeat center center","background-size":"100% auto"}},{"selectors":["c837"],"style":{"background":"url('../External/therapyTemplate/demos/therapy/images/hero-right.png') no-repeat top right","background-size":"auto 100%"}}],"pages":[{"frames":[{"component":{"type":"wrapper","stylable":["background","background-color","background-image","background-repeat","background-attachment","background-position","background-size"],"components":[{"classes":["clearfix"],"attributes":{"id":"wrapper"},"components":[{"tagName":"header","classes":["transparent-header","floating-header","dark","custom-header-size"],"attributes":{"id":"header","data-sticky-shrink":"false"},"components":[{"attributes":{"id":"header-wrap"},"components":[{"classes":["container","pe-md-0"],"components":[{"classes":["header-row"],"components":[{"classes":["me-lg-4","pe-lg-4"],"attributes":{"id":"logo"},"components":[{"type":"link","editable":false,"classes":["standard-logo"],"attributes":{"href":"index.html"},"components":[{"type":"image","attributes":{"src":"../External/therapyTemplate/demos/therapy/images/logo.png","alt":"Site Logo"}}]},{"type":"link","editable":false,"classes":["retina-logo"],"attributes":{"href":"index.html"},"components":[{"type":"image","attributes":{"src":"../External/therapyTemplate/demos/therapy/images/logo@2x.png","alt":"Site Logo"}}]}]},{"attributes":{"id":"primary-menu-trigger"},"components":[{"type":"svg","resizable":{"ratioDefault":true},"classes":["svg-trigger"],"attributes":{"viewBox":"0 0 100 100"},"components":[{"tagName":"path","type":"svg-in","resizable":{"ratioDefault":true},"attributes":{"d":"m 30,33 h 40 c 3.722839,0 7.5,3.126468 7.5,8.578427 0,5.451959 -2.727029,8.421573 -7.5,8.421573 h -20"}},{"tagName":"path","type":"svg-in","resizable":{"ratioDefault":true},"attributes":{"d":"m 30,50 h 40"}},{"tagName":"path","type":"svg-in","resizable":{"ratioDefault":true},"attributes":{"d":"m 70,67 h -40 c 0,0 -7.5,-0.802118 -7.5,-8.365747 0,-7.563629 7.5,-8.634253 7.5,-8.634253 h 20"}}]}]},{"classes":["header-misc","ms-lg-auto"],"components":[{"type":"link","classes":["fw-medium","font-primary"],"attributes":{"href":"#","data-scrollto":"#section-appointment","data-easing":"easeInOutExpo","data-speed":"1250","data-offset":"140"},"components":[{"type":"textnode","content":"Book Now"}]}]},{"tagName":"nav","classes":["primary-menu"],"components":[{"tagName":"ul","classes":["menu-container","style-2","one-page-menu"],"components":[{"tagName":"li","classes":["menu-item","border-light","current"],"components":[{"type":"link","editable":false,"classes":["menu-link"],"attributes":{"href":"#","data-easing":"easeInOutExpo","data-speed":"1250","data-offset":"0","data-href":"#slider"},"components":[{"classes":["overflow-hidden"],"components":[{"type":"text","attributes":{"data-animate":"fadeInDownSmall"},"components":[{"type":"textnode","content":"Home"}]}]}]}]},{"tagName":"li","classes":["menu-item","border-light"],"components":[{"type":"link","editable":false,"classes":["menu-link"],"attributes":{"href":"#","data-easing":"easeInOutExpo","data-speed":"1250","data-offset":"130","data-href":"#section-about"},"components":[{"classes":["overflow-hidden"],"components":[{"type":"text","attributes":{"data-animate":"fadeInDownSmall","data-delay":"200"},"components":[{"type":"textnode","content":"About"}]}]}]}]},{"tagName":"li","classes":["menu-item","border-light"],"components":[{"type":"link","editable":false,"classes":["menu-link"],"attributes":{"href":"#","data-easing":"easeInOutExpo","data-speed":"1250","data-offset":"130","data-href":"#section-services"},"components":[{"classes":["overflow-hidden"],"components":[{"type":"text","attributes":{"data-animate":"fadeInDownSmall","data-delay":"200"},"components":[{"type":"textnode","content":"Services"}]}]}]}]},{"tagName":"li","classes":["menu-item","border-light"],"components":[{"type":"link","editable":false,"classes":["menu-link"],"attributes":{"href":"#","data-easing":"easeInOutExpo","data-speed":"1250","data-offset":"0","data-href":"#section-price"},"components":[{"classes":["overflow-hidden"],"components":[{"type":"text","attributes":{"data-animate":"fadeInDownSmall","data-delay":"400"},"components":[{"type":"textnode","content":"Price"}]}]}]}]},{"tagName":"li","classes":["menu-item","border-light"],"components":[{"type":"link","editable":false,"classes":["menu-link"],"attributes":{"href":"#","data-easing":"easeInOutExpo","data-speed":"1250","data-offset":"130","data-href":"#section-testimonials"},"components":[{"classes":["overflow-hidden"],"components":[{"type":"text","attributes":{"data-animate":"fadeInDownSmall","data-delay":"600"},"components":[{"type":"textnode","content":"Testimonials"}]}]}]}]},{"tagName":"li","classes":["menu-item","border-light"],"components":[{"type":"link","editable":false,"classes":["menu-link"],"attributes":{"href":"#","data-easing":"easeInOutExpo","data-speed":"1250","data-offset":"130","data-href":"#section-shop"},"components":[{"classes":["overflow-hidden"],"components":[{"type":"text","attributes":{"data-animate":"fadeInDownSmall","data-delay":"800"},"components":[{"type":"textnode","content":"Shop"}]}]}]}]}]}]}]}]}]},{"classes":["header-wrap-clone"]}]},{"tagName":"section","classes":["slider-element","min-vh-60","min-vh-md-100","include-header","border-bottom","border-light","dark","c837"],"attributes":{"id":"slider"},"components":[{"classes":["slider-inner"],"components":[{"classes":["container"],"components":[{"classes":["row","align-items-center","h-100","mt-2","mt-lg-6"],"components":[{"classes":["col-md-6"],"components":[{"classes":["overflow-hidden"],"components":[{"tagName":"h2","type":"text","classes":["display-3","fw-normal","mb-0"],"attributes":{"data-animate":"fadeInUpSmall faster"},"components":[{"type":"textnode","content":"Your Home"}]}]},{"classes":["overflow-hidden","mb-4"],"components":[{"tagName":"h2","type":"text","classes":["display-3","fw-normal","mb-0"],"attributes":{"data-animate":"fadeInUpSmall faster","data-delay":"100"},"components":[{"type":"textnode","content":"Our Careness."}]}]},{"classes":["overflow-hidden","mb-5"],"components":[{"tagName":"p","type":"text","classes":["lead","mb-0"],"attributes":{"data-animate":"fadeInUpSmall faster","data-delay":"200"},"components":[{"type":"textnode","content":"Cum quod nam molestias eiusmod accumsan repellendus velit, nisl, mollit! Congue corrupti accusamus lorem."}]}]},{"classes":["overflow-hidden","mb-4"],"components":[{"type":"link","classes":["btn","rounded-0","btn-border","color","size-lg"],"attributes":{"href":"#","data-animate":"fadeInUpSmall faster","data-delay":"300","data-scrollto":"#section-appointment","data-easing":"easeInOutExpo","data-speed":"1250","data-offset":"140"},"components":[{"tagName":"i","classes":["icon-calendar21"]},{"tagName":"span","type":"text","components":[{"type":"textnode","content":"Make an Appointment"}]}]}]}]}]}]},{"classes":["position-absolute","d-flex","c1032"],"attributes":{"id":"ig8uf"},"components":[{"type":"link","classes":["social-icon","mx-1","si-border","si-small","border-light","si-facebook"],"attributes":{"href":"#","data-animate":"bounceInRight"},"components":[{"tagName":"i","classes":["icon-facebook"]},{"tagName":"i","classes":["icon-facebook"]}]},{"type":"link","classes":["social-icon","mx-1","si-border","si-small","border-light","si-instagram"],"attributes":{"href":"#","data-animate":"bounceInRight","data-delay":"100"},"components":[{"tagName":"i","classes":["icon-instagram"]},{"tagName":"i","classes":["icon-instagram"]}]},{"type":"link","classes":["social-icon","mx-1","si-border","si-small","border-light","si-twitter"],"attributes":{"href":"#","data-animate":"bounceInRight","data-delay":"200"},"components":[{"tagName":"i","classes":["icon-twitter"]},{"tagName":"i","classes":["icon-twitter"]}]}]}]}]},{"tagName":"section","attributes":{"id":"content"},"components":[{"classes":["content-wrap"],"components":[{"classes":["section","page-section","dark","bg-transparent"],"attributes":{"id":"section-about"},"components":[{"classes":["container","clearfix"],"components":[{"classes":["row","justify-content-center"],"components":[{"classes":["col-lg-6","mb-5","mb-lg-0"],"components":[{"classes":["overflow-hidden","mb-4"],"components":[{"tagName":"h3","type":"text","classes":["display-4","color","mb-0"],"attributes":{"data-animate":"fadeInUpSmall fast"},"components":[{"tagName":"i","classes":["spa-flowers","pe-2","text-white-50"]},{"type":"textnode","content":" About Us"}]}]},{"tagName":"blockquote","classes":["border-light","border-width-2","font-primary"],"components":[{"type":"image","classes":["alignleft","my-0"],"attributes":{"src":"../External/therapyTemplate/demos/therapy/images/about/2.jpg","alt":"Image","width":"100"}},{"type":"textnode","content":"Quo nulla condimentum sequi dictumst cupiditate culpa, quisquam placerat lorem velit repudiandae eget eaque consectetuer quidem class dolore quibusdam hic."}]},{"classes":["clear"]},{"classes":["row","mt-4"],"components":[{"classes":["col-auto"],"components":[{"tagName":"ul","classes":["list-unstyled","iconlist","ms-0"],"components":[{"tagName":"li","components":[{"tagName":"h5","type":"text","classes":["mb-3","h5"],"components":[{"type":"textnode","content":"Monday - Saturday"}]}]},{"tagName":"li","components":[{"tagName":"h5","type":"text","classes":["mb-3","h5"],"components":[{"type":"textnode","content":"6:30 - 20:00"}]}]},{"tagName":"li","components":[{"tagName":"h5","type":"text","classes":["mb-3","h5","text-white-50"],"components":[{"type":"textnode","content":"Sunday Closed"}]}]}]}]},{"classes":["col"],"components":[{"tagName":"p","type":"text","classes":["text-white-50"],"components":[{"type":"textnode","content":"Objectively facilitate synergistic initiatives vis-a-vis adaptive ideas. Enthusiastically e-enable transparent e-markets after clicks-and-mortar ideas."}]}]}]},{"classes":["row","counter-wrap","align-items-center","mt-4"],"components":[{"classes":["col-4","col-lg-4"],"components":[{"classes":["counter","color"],"components":[{"tagName":"span","attributes":{"data-from":"1","data-to":"10","data-speed":"1000"}},{"type":"textnode","content":"+"}]},{"tagName":"h5","type":"text","classes":["mb-0","font-body","text-white-50"],"components":[{"type":"textnode","content":"Years"}]}]},{"classes":["col-4","col-lg-4"],"components":[{"classes":["counter","color"],"components":[{"tagName":"span","attributes":{"data-from":"3","data-to":"32","data-speed":"1500"}}]},{"tagName":"h5","type":"text","classes":["mb-0","font-body","text-white-50"],"components":[{"type":"textnode","content":"Branches"}]}]},{"classes":["col-4","col-lg-4"],"components":[{"classes":["counter","color"],"components":[{"tagName":"span","attributes":{"data-from":"11","data-to":"154","data-refresh-interval":"50","data-speed":"1500"}},{"type":"textnode","content":"+"}]},{"tagName":"h5","type":"text","classes":["mb-0","font-body","text-white-50"],"components":[{"type":"textnode","content":"Employees"}]}]}]}]},{"classes":["col-md-5","box-img","p-2","d-none","d-lg-block"],"components":[{"classes":["h-100","rounded","c1603"],"attributes":{"id":"i8ddou"}}]}]}]}]},{"classes":["clear"]},{"classes":["section","page-section","dark","bg-transparent","m-0","pb-0"],"attributes":{"id":"section-services"},"components":[{"classes":["container"],"components":[{"classes":["row","justify-content-center","text-center"],"components":[{"classes":["col-12"],"components":[{"classes":["overflow-hidden"],"components":[{"type":"text","classes":["text-white-50","mb-2","text-uppercase","ls3"],"attributes":{"data-animate":"fadeInUpSmall","data-delay":"10"},"components":[{"type":"textnode","content":"What We Do"}]},{"tagName":"h3","type":"text","classes":["display-4","color","mb-0"],"attributes":{"data-animate":"fadeInUpSmall fast"},"components":[{"tagName":"i","classes":["spa-ointment2","color"]},{"type":"textnode","content":" Our Services"}]}]}]}]}]},{"classes":["row","dark","align-content-stretch","grid-border","topmargin"],"components":[{"classes":["col-lg-4","col-md-6","col-padding"],"components":[{"classes":["feature-box","flex-column","fbox-plain"],"components":[{"classes":["fbox-icon","mb-3","overflow-hidden"],"components":[{"tagName":"i","classes":["spa-towel"],"attributes":{"data-animate":"fadeInUpSmall fast"}}]},{"classes":["fbox-content"],"components":[{"classes":["overflow-hidden","mb-3"],"components":[{"tagName":"h2","type":"text","classes":["h3","text-white","mb-0"],"attributes":{"data-animate":"fadeInUpSmall fast","data-delay":"100"},"components":[{"type":"textnode","content":"Shower Available"}]}]},{"classes":["overflow-hidden"],"components":[{"tagName":"p","type":"text","classes":["mb-0"],"attributes":{"data-animate":"fadeInUpSmall fast","data-delay":"200"},"components":[{"type":"textnode","content":"Lorem ipsum dolor sit amet, consectetur adipisicing elit. Voluptas omnis nam molestias minus ipsa, placeat!"}]}]}]}]}]},{"classes":["col-lg-4","col-md-6","col-padding"],"components":[{"classes":["feature-box","flex-column","fbox-plain"],"components":[{"classes":["fbox-icon","mb-3","overflow-hidden"],"components":[{"tagName":"i","classes":["spa-sandals"],"attributes":{"data-animate":"fadeInUpSmall fast"}}]},{"classes":["fbox-content"],"components":[{"classes":["overflow-hidden","mb-3"],"components":[{"tagName":"h2","type":"text","classes":["h3","text-white","mb-0"],"attributes":{"data-animate":"fadeInUpSmall fast","data-delay":"100"},"components":[{"type":"textnode","content":"Foot Treatments"}]}]},{"classes":["overflow-hidden","mb-3"],"components":[{"tagName":"p","type":"text","classes":["mb-0"],"attributes":{"data-animate":"fadeInUpSmall fast","data-delay":"200"},"components":[{"type":"textnode","content":"Facere aliquam itaque quia recusandae, corporis fugit fugiat eaque, accusamus officiis reprehenderit."}]}]}]}]}]},{"classes":["col-lg-4","col-md-6","col-padding"],"components":[{"classes":["feature-box","flex-column","fbox-plain"],"components":[{"classes":["fbox-icon","mb-3","overflow-hidden"],"components":[{"tagName":"i","classes":["spa-cup-flower"],"attributes":{"data-animate":"fadeInUpSmall fast"}}]},{"classes":["fbox-content"],"components":[{"classes":["overflow-hidden","mb-3"],"components":[{"tagName":"h2","type":"text","classes":["h3","text-white","mb-0"],"attributes":{"data-animate":"fadeInUpSmall fast","data-delay":"100"},"components":[{"type":"textnode","content":"Internal Beautification"}]}]},{"classes":["overflow-hidden","mb-3"],"components":[{"tagName":"p","type":"text","classes":["mb-0"],"attributes":{"data-animate":"fadeInUpSmall fast","data-delay":"200"},"components":[{"type":"textnode","content":"Velit id facilis odit aliquid laudantium. Tempore, sequi. Harum nesciunt, magni aperiam est?"}]}]}]}]}]},{"classes":["col-lg-4","col-md-6","col-padding"],"components":[{"classes":["feature-box","flex-column","fbox-plain"],"components":[{"classes":["fbox-icon","mb-3","overflow-hidden"],"components":[{"tagName":"i","classes":["spa-meditation"],"attributes":{"data-animate":"fadeInUpSmall fast"}}]},{"classes":["fbox-content"],"components":[{"classes":["overflow-hidden","mb-3"],"components":[{"tagName":"h2","type":"text","classes":["h3","text-white","mb-0"],"attributes":{"data-animate":"fadeInUpSmall fast","data-delay":"100"},"components":[{"type":"textnode","content":"Yoga & Meditation"}]}]},{"classes":["overflow-hidden","mb-3"],"components":[{"tagName":"p","type":"text","classes":["mb-0"],"attributes":{"data-animate":"fadeInUpSmall fast","data-delay":"200"},"components":[{"type":"textnode","content":"Voluptatum distinctio laboriosam, excepturi delectus nam fugit obcaecati reiciendis neque iste!"}]}]}]}]}]},{"classes":["col-lg-4","col-md-6","col-padding"],"components":[{"classes":["feature-box","flex-column","fbox-plain"],"components":[{"classes":["fbox-icon","mb-3","overflow-hidden"],"components":[{"tagName":"i","classes":["spa-comb"],"attributes":{"data-animate":"fadeInUpSmall fast"}}]},{"classes":["fbox-content"],"components":[{"classes":["overflow-hidden","mb-3"],"components":[{"tagName":"h2","type":"text","classes":["h3","text-white","mb-0"],"attributes":{"data-animate":"fadeInUpSmall fast","data-delay":"100"},"components":[{"type":"textnode","content":"Hair Dressing"}]}]},{"classes":["overflow-hidden","mb-3"],"components":[{"tagName":"p","type":"text","classes":["mb-0"],"attributes":{"data-animate":"fadeInUpSmall fast","data-delay":"200"},"components":[{"type":"textnode","content":"Quis, tenetur. Nam explicabo modi pariatur, blanditiis distinctio sapiente fugiat accusantium."}]}]}]}]}]},{"classes":["col-lg-4","col-md-6","col-padding"],"components":[{"classes":["feature-box","flex-column","fbox-plain"],"components":[{"classes":["fbox-icon","mb-3","overflow-hidden"],"components":[{"tagName":"i","classes":["spa-flowers-feet"],"attributes":{"data-animate":"fadeInUpSmall fast"}}]},{"classes":["fbox-content"],"components":[{"classes":["overflow-hidden","mb-3"],"components":[{"tagName":"h2","type":"text","classes":["h3","text-white","mb-0"],"attributes":{"data-animate":"fadeInUpSmall fast","data-delay":"100"},"components":[{"type":"textnode","content":"Herbal Pedicure"}]}]},{"classes":["overflow-hidden","mb-3"],"components":[{"tagName":"p","type":"text","classes":["mb-0"],"attributes":{"data-animate":"fadeInUpSmall fast","data-delay":"200"},"components":[{"type":"textnode","content":"Veniam atque corporis commodi. Quidem odit, necessitatibus quo tenetur! Harum similique illo eligendi!"}]}]}]}]}]}]}]},{"classes":["clear"]},{"classes":["section","page-section","dark","mt-0","pb-0","overflow-visible","c2357"],"attributes":{"id":"section-price"},"components":[{"classes":["container"],"components":[{"classes":["row","justify-content-end","mx-auto","mw-md","c2375"],"attributes":{"id":"i4kd5v"},"components":[{"classes":["col-lg-5","col-md-7"],"components":[{"tagName":"p","type":"text","classes":["border","border-light","p-2","d-inline","text-smaller"],"components":[{"type":"textnode","content":"Members get -40% off Instant Discount"}]},{"tagName":"h3","type":"text","classes":["display-4","mt-2","text-white"],"components":[{"tagName":"i","classes":["spa-cost","pe-2"]},{"type":"textnode","content":"Pricing"}]},{"classes":["card","bg-color","border-light","shadow-lg"],"components":[{"classes":["card-body","p-4"],"components":[{"classes":["overflow-hidden"],"components":[{"classes":["row","align-items-center"],"attributes":{"data-animate":"fadeInUpSmall faster"},"components":[{"classes":["col-3"],"components":[{"type":"image","classes":["rounded"],"attributes":{"src":"../External/therapyTemplate/demos/therapy/images/price/swedish.jpg","alt":"Image"}}]},{"classes":["col-9"],"components":[{"tagName":"h4","type":"text","classes":["mb-2"],"components":[{"type":"textnode","content":"Swedish Massage"}]},{"classes":["d-flex","align-middle","text-smaller"],"components":[{"components":[{"tagName":"span","type":"text","classes":["op-04"],"components":[{"type":"textnode","content":"60 Mins:"}]},{"tagName":"span","type":"text","classes":["font-primary","ms-2"],"components":[{"type":"textnode","content":"$39"}]}]},{"tagName":"small","components":[{"tagName":"i","classes":["icon-circle","text-smaller","op-02","mx-3"]}]},{"components":[{"tagName":"span","type":"text","classes":["op-04"],"components":[{"type":"textnode","content":"120 Mins:"}]},{"tagName":"span","type":"text","classes":["font-primary","ms-2"],"components":[{"type":"textnode","content":"$59"}]}]}]}]}]}]},{"classes":["line","my-4"]},{"classes":["overflow-hidden"],"components":[{"classes":["row","align-items-center"],"attributes":{"data-animate":"fadeInUpSmall faster","data-delay":"50"},"components":[{"classes":["col-3"],"components":[{"type":"image","classes":["rounded"],"attributes":{"src":"../External/therapyTemplate/demos/therapy/images/price/scrub.jpg","alt":"Image"}}]},{"classes":["col-9"],"components":[{"tagName":"h4","type":"text","classes":["mb-2"],"components":[{"type":"textnode","content":"Body Scrub"}]},{"classes":["d-flex","align-middle","text-smaller"],"components":[{"components":[{"tagName":"span","type":"text","classes":["op-04"],"components":[{"type":"textnode","content":"60 Mins:"}]},{"tagName":"span","type":"text","classes":["font-primary","ms-2"],"components":[{"type":"textnode","content":"$39"}]}]},{"tagName":"small","components":[{"tagName":"i","classes":["icon-circle","text-smaller","op-02","mx-3"]}]},{"components":[{"tagName":"span","type":"text","classes":["op-04"],"components":[{"type":"textnode","content":"120 Mins:"}]},{"tagName":"span","type":"text","classes":["font-primary","ms-2"],"components":[{"type":"textnode","content":"$59"}]}]}]}]}]}]},{"classes":["line","my-4"]},{"classes":["overflow-hidden"],"components":[{"classes":["row","align-items-center"],"attributes":{"data-animate":"fadeInUpSmall faster","data-delay":"100"},"components":[{"classes":["col-3"],"components":[{"type":"image","classes":["rounded"],"attributes":{"src":"../External/therapyTemplate/demos/therapy/images/price/couple-spa.jpg","alt":"Image"}}]},{"classes":["col-9"],"components":[{"tagName":"h4","type":"text","classes":["mb-2"],"components":[{"type":"textnode","content":"Couple Massage"}]},{"classes":["d-flex","align-middle","text-smaller"],"components":[{"components":[{"tagName":"span","type":"text","classes":["op-04"],"components":[{"type":"textnode","content":"60 Mins:"}]},{"tagName":"span","type":"text","classes":["font-primary","ms-2"],"components":[{"type":"textnode","content":"$39"}]}]},{"tagName":"small","components":[{"tagName":"i","classes":["icon-circle","text-smaller","op-02","mx-3"]}]},{"components":[{"tagName":"span","type":"text","classes":["op-04"],"components":[{"type":"textnode","content":"120 Mins:"}]},{"tagName":"span","type":"text","classes":["font-primary","ms-2"],"components":[{"type":"textnode","content":"$59"}]}]}]}]}]}]},{"classes":["line","my-4"]},{"classes":["overflow-hidden"],"components":[{"classes":["row","align-items-center"],"attributes":{"data-animate":"fadeInUpSmall faster","data-delay":"150"},"components":[{"classes":["col-3"],"components":[{"type":"image","classes":["rounded"],"attributes":{"src":"../External/therapyTemplate/demos/therapy/images/price/hot-stone.jpg","alt":"Image"}}]},{"classes":["col-9"],"components":[{"tagName":"h4","type":"text","classes":["mb-2"],"components":[{"type":"textnode","content":"Hot Stone Therapy"}]},{"classes":["d-flex","align-middle","text-smaller"],"components":[{"components":[{"tagName":"span","type":"text","classes":["op-04"],"components":[{"type":"textnode","content":"60 Mins:"}]},{"tagName":"span","type":"text","classes":["font-primary","ms-2"],"components":[{"type":"textnode","content":"$39"}]}]},{"tagName":"small","components":[{"tagName":"i","classes":["icon-circle","text-smaller","op-02","mx-3"]}]},{"components":[{"tagName":"span","type":"text","classes":["op-04"],"components":[{"type":"textnode","content":"120 Mins:"}]},{"tagName":"span","type":"text","classes":["font-primary","ms-2"],"components":[{"type":"textnode","content":"$59"}]}]}]}]}]}]},{"type":"link","classes":["btn","rounded-0","btn-border","color","w-100","size-sm","mt-4"],"attributes":{"href":"#"},"components":[{"tagName":"span","type":"text","classes":["flex-grow-1","font-body"],"components":[{"type":"textnode","content":"View All"}]},{"tagName":"i","classes":["icon-line-arrow-right","border-start","border-light","border-end-0"]}]}]}]}]}]}]}]},{"classes":["clear"]},{"classes":["section","page-section","bg-transparent","topmargin-lg"],"attributes":{"id":"section-appointment"},"components":[{"classes":["container","mw-md"],"components":[{"classes":["row","align-items-stretch"],"components":[{"classes":["col-md-6","min-vh-50","d-flex","flex-column"],"components":[{"classes":["h-50","rounded","mt-2","px-5","c3313"],"attributes":{"id":"i6duxw"},"components":[{"classes":["vertical-middle","over"],"components":[{"classes":["overflow-hidden"],"components":[{"type":"text","classes":["text-black-50"],"attributes":{"data-animate":"fadeInUpSmall fast"},"components":[{"type":"textnode","content":"Cosmetics"}]}]},{"classes":["overflow-hidden"],"components":[{"tagName":"h3","type":"text","classes":["h3","mb-0","mt-1"],"attributes":{"data-animate":"fadeInUpSmall fast","data-delay":"100"},"components":[{"type":"textnode","content":"Face Cream"}]}]},{"classes":["overflow-hidden"],"components":[{"type":"link","classes":["button","button-dark","bg-color","mt-3"],"attributes":{"href":"#","data-animate":"fadeInUpSmall fast","data-delay":"200"},"components":[{"type":"textnode","content":"Shop Now"}]}]}]}]},{"classes":["h-50","rounded","text-lg-end","px-4","mt-4","c3423"],"attributes":{"id":"i7627w"},"components":[{"classes":["vertical-middle"],"components":[{"classes":["overflow-hidden"],"components":[{"type":"text","classes":["text-black-50"],"attributes":{"data-animate":"fadeInUpSmall fast"},"components":[{"type":"textnode","content":"Spa Products"}]}]},{"classes":["overflow-hidden"],"components":[{"tagName":"h3","type":"text","classes":["h3","mb-0","mt-1"],"attributes":{"data-animate":"fadeInUpSmall fast","data-delay":"100"},"components":[{"type":"textnode","content":"Relieve Stress"}]}]},{"classes":["overflow-hidden"],"components":[{"type":"link","classes":["button","button-dark","bg-color","mt-3"],"attributes":{"href":"#","data-animate":"fadeInUpSmall fast","data-delay":"200"},"components":[{"type":"textnode","content":"Shop Now"}]}]}]}]}]},{"classes":["col-md-6","mt-5","mt-md-0"],"components":[{"classes":["dark"],"components":[{"classes":["d-flex","align-items-center","bottommargin-sm"],"components":[{"tagName":"i","classes":["spa-leaves","h3","icon-stacked","text-center","border","border-light","color","rounded-circle","icon-2x","me-3","mb-0"]},{"components":[{"classes":["overflow-hidden"],"components":[{"type":"text","classes":["text-white-50"],"attributes":{"data-animate":"fadeInUpSmall","data-delay":"10"},"components":[{"type":"textnode","content":"Get Instant 40% Discount"}]}]},{"classes":["overflow-hidden"],"components":[{"tagName":"h3","type":"text","classes":["h3","mb-0","mt-1"],"attributes":{"data-animate":"fadeInUpSmall","data-delay":"100"},"components":[{"type":"textnode","content":"Make an Appointment"}]}]}]}]},{"classes":["form-widget"],"components":[{"classes":["form-result"]},{"type":"form","classes":["mb-0"],"attributes":{"method":"post","id":"template-contactform","name":"template-contactform","action":"include/form.php"},"components":[{"classes":["form-process"],"components":[{"classes":["css3-spinner"],"components":[{"classes":["css3-spinner-scaler"]}]}]},{"classes":["row"],"components":[{"classes":["col-md-12","form-group"],"components":[{"type":"input","void":true,"classes":["form-control","form-control-lg","bg-transparent","color","border-light","required"],"attributes":{"type":"text","id":"template-contactform-name","name":"template-contactform-name","value":"","placeholder":"Your Name"}}]},{"classes":["col-md-12","form-group"],"components":[{"type":"input","void":true,"classes":["form-control","form-control-lg","required","bg-transparent","color","border-light"],"attributes":{"type":"email","id":"template-contactform-email","name":"template-contactform-email","value":"","placeholder":"Email Address "}}]},{"classes":["col-md-12","form-group"],"components":[{"type":"input","void":true,"classes":["form-control","form-control-lg","bg-transparent","color","border-light"],"attributes":{"type":"text","id":"template-contactform-phone","name":"template-contactform-phone","value":"","placeholder":"Contact Number"}}]},{"classes":["col-md-12","form-group"],"components":[{"type":"select","classes":["form-select","form-select-lg","bg-transparent","color","border-light"],"attributes":{"type":"text","id":"template-contactform-service","name":"template-contactform-service"},"components":[{"type":"option","attributes":{"disabled":true,"selected":true,"value":""},"components":[{"type":"textnode","content":"Select Your Service"}]},{"type":"option","attributes":{"value":"Swedish Massage"},"components":[{"type":"textnode","content":"Swedish Massage"}]},{"type":"option","attributes":{"value":"Body Scrub"},"components":[{"type":"textnode","content":"Body Scrub"}]},{"type":"option","attributes":{"value":"Couple Massage"},"components":[{"type":"textnode","content":"Couple Massage"}]},{"type":"option","attributes":{"value":"Hot Stone Therapy"},"components":[{"type":"textnode","content":"Hot Stone Therapy"}]}]}]},{"classes":["col-md-12","form-group"],"components":[{"type":"input","void":true,"classes":["form-control","form-control-lg","bg-transparent","color","border-light","required"],"attributes":{"type":"text","id":"template-contactform-date","name":"template-contactform-date","value":"","placeholder":"Select Date & Time..","data-time":"true","data-dateformat":"d/m/yy - H:i"}}]},{"classes":["col-12","form-group","d-none"],"components":[{"type":"input","void":true,"classes":["form-control","form-control-lg","bg-transparent","color","border-light"],"attributes":{"type":"text","id":"template-contactform-botcheck","name":"template-contactform-botcheck","value":""}}]},{"classes":["col-12"],"components":[{"type":"button","classes":["btn","rounded-0","btn-border","color","w-100"],"attributes":{"type":"submit","id":"template-contactform-submit","name":"template-contactform-submit","value":"submit"},"components":[{"type":"textnode","content":"Send"}]}]}]},{"type":"input","void":true,"attributes":{"type":"hidden","name":"prefix","value":"template-contactform-"}}]}]}]}]}]}]}]},{"classes":["clear"]},{"classes":["section","page-section","bg-transparent","mt-0"],"attributes":{"id":"section-testimonials"},"components":[{"classes":["container"],"components":[{"classes":["row","justify-content-center","text-center"],"attributes":{"data-animate":"fadeIn"},"components":[{"classes":["col-12"],"components":[{"classes":["overflow-hidden"],"components":[{"type":"text","classes":["text-white-50","mb-2","text-uppercase","ls3"],"attributes":{"data-animate":"fadeInUpSmall","data-delay":"100"},"components":[{"type":"textnode","content":"What Our Client Say"}]},{"tagName":"h3","type":"text","classes":["display-4","color","mb-0"],"attributes":{"data-animate":"fadeInUpSmall fast","data-delay":"200"},"components":[{"tagName":"i","classes":["spa-facial","pe-2","color"]},{"type":"textnode","content":" Client Testimonials"}]}]},{"type":"link","classes":["btn","rounded-0","btn-border","color","mt-4"],"attributes":{"href":"https://google.com","data-animate":"fadeInUpSmall","data-delay":"300"},"components":[{"tagName":"i","classes":["spa-star"]},{"tagName":"span","type":"text","classes":["px-4"],"components":[{"type":"textnode","content":"2,312+ Google Reviews"}]}]}]}]}]},{"classes":["owl-carousel","carousel-widget","dark","topmargin","border-bottom","border-top","border-light","c4148"],"attributes":{"id":"oc-testi","data-items-xl":"3","data-items-lg":"3","data-items-md":"2","data-items-xs":"1","data-pagi":"false","data-loop":"true","data-margin":"0"},"components":[{"classes":["oc-item","p-5","d-flex","flex-column","text-center"],"components":[{"classes":["testi-image","mx-auto","overflow-hidden"],"components":[{"type":"link","editable":false,"classes":["data-animate"],"attributes":{"href":"#"},"components":[{"type":"image","attributes":{"src":"../External/therapyTemplate/demos/therapy/images/users/1.jpg","alt":"Customer Testimonails"}}]}]},{"classes":["testi-content"],"components":[{"classes":["overflow-hidden"],"components":[{"tagName":"p","type":"text","classes":["data-animate"],"components":[{"type":"textnode","content":"Incidunt deleniti blanditiis quas aperiam recusandae consequatur ullam quibusdam cum libero illo rerum repellendus!"}]}]},{"type":"text","classes":["testi-meta","data-animate"],"components":[{"type":"textnode","content":"\nJim Séchen\n"},{"tagName":"span","type":"text","components":[{"type":"textnode","content":"XYZ Inc."}]}]}]}]},{"classes":["oc-item","p-5","d-flex","flex-column","text-center"],"components":[{"classes":["testi-image","mx-auto","overflow-hidden"],"components":[{"type":"link","editable":false,"attributes":{"href":"#"},"components":[{"type":"image","attributes":{"src":"../External/therapyTemplate/demos/therapy/images/users/2.jpg","alt":"Customer Testimonails"}}]}]},{"classes":["testi-content"],"components":[{"classes":["overflow-hidden"],"components":[{"tagName":"p","type":"text","components":[{"type":"textnode","content":"Natus voluptatum enim quod necessitatibus quis expedita harum provident eos obcaecati id culpa corporis molestias."}]}]},{"type":"text","classes":["testi-meta"],"components":[{"type":"textnode","content":"\nAlan Fresco\n"},{"tagName":"span","type":"text","components":[{"type":"textnode","content":"Company Inc."}]}]}]}]},{"classes":["oc-item","p-5","d-flex","flex-column","text-center"],"components":[{"classes":["testi-image","mx-auto","overflow-hidden"],"components":[{"type":"link","editable":false,"attributes":{"href":"#"},"components":[{"type":"image","attributes":{"src":"../External/therapyTemplate/demos/therapy/images/users/7.jpg","alt":"Customer Testimonails"}}]}]},{"classes":["testi-content"],"components":[{"classes":["overflow-hidden"],"components":[{"tagName":"p","type":"text","components":[{"type":"textnode","content":"Fugit officia dolor sed harum excepturi ex iusto magnam asperiores molestiae qui natus obcaecati facere sint amet."}]}]},{"type":"text","classes":["testi-meta"],"components":[{"type":"textnode","content":"\nFig Nelson\n"},{"tagName":"span","type":"text","components":[{"type":"textnode","content":"Google Inc."}]}]}]}]},{"classes":["oc-item","p-5","d-flex","flex-column","text-center"],"components":[{"classes":["testi-image","mx-auto","overflow-hidden"],"components":[{"type":"link","editable":false,"attributes":{"href":"#"},"components":[{"type":"image","attributes":{"src":"../External/therapyTemplate/demos/therapy/images/users/3.jpg","alt":"Customer Testimonails"}}]}]},{"classes":["testi-content"],"components":[{"classes":["overflow-hidden"],"components":[{"tagName":"p","type":"text","components":[{"type":"textnode","content":"Similique fugit repellendus expedita excepturi iure perferendis provident quia eaque. Repellendus, vero numquam?"}]}]},{"type":"text","classes":["testi-meta"],"components":[{"type":"textnode","content":"\nPelican Steve\n"},{"tagName":"span","type":"text","components":[{"type":"textnode","content":"Apple Inc."}]}]}]}]},{"classes":["oc-item","p-5","d-flex","flex-column","text-center"],"components":[{"classes":["testi-image","mx-auto","overflow-hidden"],"components":[{"type":"link","editable":false,"attributes":{"href":"#"},"components":[{"type":"image","attributes":{"src":"../External/therapyTemplate/demos/therapy/images/users/4.jpg","alt":"Customer Testimonails"}}]}]},{"classes":["testi-content"],"components":[{"classes":["overflow-hidden"],"components":[{"tagName":"p","type":"text","components":[{"type":"textnode","content":"Lorem ipsum dolor sit amet, consectetur adipisicing elit. Minus, perspiciatis illum totam dolore deleniti labore."}]}]},{"type":"text","classes":["testi-meta"],"components":[{"type":"textnode","content":"\nRussell Sprout\n"},{"tagName":"span","type":"text","components":[{"type":"textnode","content":"Adobe Inc."}]}]}]}]}]}]},{"classes":["clear"]},{"classes":["section","page-section","dark","bg-transparent","m-0"],"attributes":{"id":"section-shop"},"components":[{"classes":["container","clearfix"],"components":[{"classes":["row","justify-content-between","gutter-50"],"components":[{"classes":["col-md-6"],"components":[{"classes":["h-100","min-vh-50","rounded","c4754"],"attributes":{"id":"ivfzgi"}}]},{"classes":["col-md-6"],"components":[{"classes":["overflow-hidden","mb-4"],"components":[{"tagName":"i","classes":["spa-ointment","icon-4x","color"]},{"tagName":"h3","type":"text","classes":["display-4","color","mb-0"],"attributes":{"data-animate":"fadeInUpSmall fast"},"components":[{"type":"textnode","content":"Our Products"}]}]},{"tagName":"h5","type":"text","classes":["text-white","h6","mb-4"],"components":[{"tagName":"i","classes":["spa-sale1"]},{"type":"textnode","content":" 40% Discount for Members"}]},{"tagName":"p","type":"text","classes":["text-white-50"],"attributes":{"data-animate":"fadeInUpSmall fast"},"components":[{"type":"textnode","content":"Ipsa felis in mollis turpis phasellus, repellat! Ducimus porttitor class quod? Iste neque lorem tenetur quisque possimus excepturi error ligula."}]},{"tagName":"p","type":"text","classes":["text-white-50"],"attributes":{"data-animate":"fadeInUpSmall fast","data-delay":"200"},"components":[{"type":"textnode","content":"In morbi risus litora numquam, similique libero ligula nostrum nulla repudiandae proin luctus class varius volutpat! Fringilla fringilla sagittis nunc."}]},{"classes":["overflow-hidden","mb-4"],"components":[{"type":"link","classes":["btn","rounded-0","btn-border","color"],"attributes":{"href":"https://amazon.com","data-animate":"fadeInUpSmall faster","data-delay":"300"},"components":[{"tagName":"i","classes":["spa-flowers-feet"]},{"tagName":"span","type":"text","classes":["px-4"],"components":[{"type":"textnode","content":"Shop Now"}]}]}]}]}]}]}]}]}]},{"tagName":"footer","classes":["bg-transparent","border-width-1","border-light","dark"],"attributes":{"id":"footer"},"components":[{"classes":["container"],"components":[{"classes":["footer-widgets-wrap"],"components":[{"classes":["row","justify-content-between","col-mb-30"],"components":[{"classes":["col-lg-4","col-sm-6"],"components":[{"classes":["widget","clearfix","c4980"],"attributes":{"id":"irnhdl"},"components":[{"components":[{"tagName":"h3","type":"text","components":[{"type":"textnode","content":"About Us:"}]},{"tagName":"address","components":[{"tagName":"p","type":"text","components":[{"type":"textnode","content":"795 Folsom Ave, "},{"tagName":"br","void":true},{"type":"textnode","content":" Suite 600\nSan Francisco, CA 94107"}]}]},{"tagName":"ul","classes":["list-unstyled"],"components":[{"tagName":"li","type":"text","classes":["mb-1"],"components":[{"tagName":"span","type":"text","classes":["color","op-07"],"components":[{"type":"textnode","content":"Phone:"}]},{"type":"textnode","content":" "},{"tagName":"span","type":"text","classes":["font-primary"],"components":[{"type":"textnode","content":"(1) 8547 632521"}]}]},{"tagName":"li","classes":["mb-1"],"components":[{"tagName":"span","type":"text","classes":["color","op-07"],"components":[{"type":"textnode","content":"Email:"}]},{"type":"textnode","content":" "},{"tagName":"span","classes":["font-primary"],"components":[{"type":"link","classes":["__cf_email__"],"attributes":{"href":"/cdn-cgi/l/email-protection","data-cfemail":"147a7b667164786d5477757a6275673a777b79"},"components":[{"type":"textnode","content":"[email protected]"}]}]}]},{"tagName":"li","type":"text","components":[{"tagName":"span","type":"text","classes":["color","op-07"],"components":[{"type":"textnode","content":"WebSite:"}]},{"type":"textnode","content":" "},{"type":"link","editable":false,"attributes":{"href":"https://semicolonweb.com"},"components":[{"type":"textnode","content":" "},{"tagName":"span","type":"text","classes":["font-primary"],"components":[{"type":"textnode","content":"semicolonweb.com"}]}]}]}]},{"type":"link","classes":["social-icon","si-small","si-light","si-facebook"],"attributes":{"href":"#"},"components":[{"tagName":"i","classes":["icon-facebook"]},{"tagName":"i","classes":["icon-facebook"]}]},{"type":"link","classes":["social-icon","si-small","si-light","si-twitter"],"attributes":{"href":"#"},"components":[{"tagName":"i","classes":["icon-twitter"]},{"tagName":"i","classes":["icon-twitter"]}]},{"type":"link","classes":["social-icon","si-small","si-light","si-gplus"],"attributes":{"href":"#"},"components":[{"tagName":"i","classes":["icon-gplus"]},{"tagName":"i","classes":["icon-gplus"]}]},{"type":"link","classes":["social-icon","si-small","si-light","si-pinterest"],"attributes":{"href":"#"},"components":[{"tagName":"i","classes":["icon-pinterest"]},{"tagName":"i","classes":["icon-pinterest"]}]}]}]}]},{"classes":["col-lg-3","col-sm-6"],"components":[{"classes":["widget","widget_links","clearfix"],"components":[{"tagName":"h4","type":"text","components":[{"type":"textnode","content":"Links"}]},{"tagName":"ul","components":[{"tagName":"li","components":[{"type":"link","attributes":{"href":"#"},"components":[{"type":"textnode","content":"Home"}]}]},{"tagName":"li","components":[{"type":"link","attributes":{"href":"#"},"components":[{"type":"textnode","content":"About"}]}]},{"tagName":"li","components":[{"type":"link","attributes":{"href":"#"},"components":[{"type":"textnode","content":"Testimonials"}]}]},{"tagName":"li","components":[{"type":"link","attributes":{"href":"#"},"components":[{"type":"textnode","content":"Price"}]}]},{"tagName":"li","components":[{"type":"link","attributes":{"href":"#"},"components":[{"type":"textnode","content":"Gallery"}]}]},{"tagName":"li","components":[{"type":"link","attributes":{"href":"#"},"components":[{"type":"textnode","content":"Shop"}]}]},{"tagName":"li","components":[{"type":"link","attributes":{"href":"#"},"components":[{"type":"textnode","content":"Contact"}]}]}]}]}]},{"classes":["col-lg-5","col-md-12"],"components":[{"classes":["widget","clearfix","text-lg-end"],"components":[{"components":[{"type":"image","classes":["mb-4"],"attributes":{"src":"../External/therapyTemplate/demos/therapy/images/logo-footer.png","alt":"Image","height":"35"}},{"tagName":"p","type":"text","classes":["text-white-50","mb-5"],"components":[{"type":"textnode","content":"Lorem ipsum dolor sit amet consectetur adipisicing elit. Dicta ratione eveniet, reiciendis ut ipsam architecto neque numquam officiis mollitia. Eveniet eum aliquam quas illum id necessitatibus illo ut architecto unde."}]},{"classes":["row","justify-content-between","border","border-light"],"components":[{"classes":["col-4","py-3","text-center","border-end","border-light","overflow-hidden"],"components":[{"tagName":"h5","type":"text","classes":["mb-0"],"attributes":{"data-animate":"fadeInUpSmall faster"},"components":[{"type":"textnode","content":"Mon - Sat"}]}]},{"classes":["col-4","py-3","text-center","border-end","border-light","overflow-hidden"],"components":[{"tagName":"h5","type":"text","classes":["mb-0"],"attributes":{"data-animate":"fadeInUpSmall faster","data-delay":"100"},"components":[{"type":"textnode","content":"06:30 - 20:00"}]}]},{"classes":["col-4","py-3","text-center","overflow-hidden"],"components":[{"tagName":"h5","type":"text","classes":["mb-0","text-white-50"],"attributes":{"data-animate":"fadeInUpSmall faster","data-delay":"200"},"components":[{"type":"textnode","content":"Sunday Closed"}]}]}]}]}]}]}]}]}]},{"classes":["bg-transparent","border-top","border-light"],"attributes":{"id":"copyrights"},"components":[{"classes":["container","clearfix"],"components":[{"classes":["row","justify-content-center"],"components":[{"classes":["col-md-6","text-center"],"components":[{"tagName":"p","type":"text","classes":["mb-0"],"components":[{"type":"textnode","content":"Copyrights © 2020 All Rights Reserved by TechSite."}]},{"classes":["overflow-hidden"],"components":[{"type":"text","classes":["copyright-links"],"attributes":{"data-animate":"fadeInUpSmall faster","data-delay":"200"},"components":[{"type":"link","attributes":{"href":"#"},"components":[{"type":"textnode","content":"Terms of Use"}]},{"type":"textnode","content":" / "},{"type":"link","attributes":{"href":"#"},"components":[{"type":"textnode","content":"Privacy Policy"}]}]}]}]}]}]}]}]}]},{"classes":["icon-angle-up"],"attributes":{"id":"gotoTop"}}]}}],"id":"index"}]}